tlrx_accumulated_local_effect/__init__.py
tlrx_accumulated_local_effect/__main__.py
tlrx_accumulated_local_effect/algo.meta.json
tlrx_accumulated_local_effect/algo.py
tlrx_accumulated_local_effect/algo_init.py
tlrx_accumulated_local_effect/input.schema.json
tlrx_accumulated_local_effect/output.schema.json
tlrx_accumulated_local_effect/plugin_init.py
tlrx_accumulated_local_effect/syntax_checker.py
tlrx_accumulated_local_effect/ci/createBadges.py
tlrx_accumulated_local_effect/ci/run-flake8.sh
tlrx_accumulated_local_effect/ci/run-pip-audit.sh
tlrx_accumulated_local_effect/ci/run-test.sh
tlrx_accumulated_local_effect-2.0.0a1.dist-info/METADATA
tlrx_accumulated_local_effect-2.0.0a1.dist-info/WHEEL
tlrx_accumulated_local_effect-2.0.0a1.dist-info/entry_points.txt
tlrx_accumulated_local_effect-2.0.0a1.dist-info/licenses/AUTHORS.rst
tlrx_accumulated_local_effect-2.0.0a1.dist-info/licenses/LICENSE
tlrx_accumulated_local_effect-2.0.0a1.dist-info/RECORD
