Metadata-Version: 2.3
Name: tlrx-accumulated-local-effect
Version: 2.0.0a1
Summary: AI Verify implementation of the Accumulated Local Effect algorithm. The algorithm provides black box explainations of how features and their corresponding values influence the prediction of a model.
Author: AI Verify
License-File: AUTHORS.rst
License-File: LICENSE
Requires-Python: <3.12,>=3.10
Requires-Dist: numpy==1.26.4
Requires-Dist: pandas==2.2.2
Requires-Dist: tlrx-test-engine==2.0.0a1
